{
    "Response": {
        "vendor": {
            "privacy": 2
        },
        "categories": {
            "privacy": 2
        },
        "sales": {
            "privacy": 2
        },
        "itemComponents": {
            "perks": {
                "data": {
                    "2": {
                        "perks": [{
                            "perkHash": 2965563642,
                            "iconPath": "",
                            "isActive": true,
                            "visible": false
                        }, {
                            "perkHash": 2017119434,
                            "iconPath": "",
                            "isActive": true,
                            "visible": false
                        }, {
                            "perkHash": 3544889160,
                            "iconPath": "/common/destiny2_content/icons/7d27d5a3859284c96a4be54db2936710.png",
                            "isActive": true,
                            "visible": true
                        }, {
                            "perkHash": 128516240,
                            "iconPath": "",
                            "isActive": true,
                            "visible": false
                        }, {
                            "perkHash": 3712552436,
                            "iconPath": "/common/destiny2_content/icons/ba833d17f4b85ef723eaa7f0e5a253db.png",
                            "isActive": true,
                            "visible": true
                        }, {
                            "perkHash": 3469836202,
                            "iconPath": "",
                            "isActive": true,
                            "visible": false
                        }]
                    },
                    "33": {
                        "perks": [{
                            "perkHash": 3435464613,
                            "iconPath": "",
                            "isActive": true,
                            "visible": false
                        }, {
                            "perkHash": 3562839833,
                            "iconPath": "/common/destiny2_content/icons/ad56b0e83d31592d9984cdf2f392452a.png",
                            "isActive": true,
                            "visible": true
                        }, {
                            "perkHash": 850803125,
                            "iconPath": "/common/destiny2_content/icons/83e206ebea83f76d9969efea7134ddcc.png",
                            "isActive": true,
                            "visible": true
                        }, {
                            "perkHash": 2161792065,
                            "iconPath": "/common/destiny2_content/icons/5b83b3c3fc474c9716e54b4dfe4a862b.png",
                            "isActive": true,
                            "visible": true
                        }]
                    },
                    "43": {
                        "perks": [{
                            "perkHash": 1717910801,
                            "iconPath": "",
                            "isActive": true,
                            "visible": false
                        }, {
                            "perkHash": 3672760533,
                            "iconPath": "/common/destiny2_content/icons/90c4f7f35c9d24f4add016722a78404e.png",
                            "isActive": true,
                            "visible": true
                        }, {
                            "perkHash": 402655312,
                            "iconPath": "/common/destiny2_content/icons/df460693665b7b4dd42f1706e5fbb9e1.png",
                            "isActive": true,
                            "visible": true
                        }, {
                            "perkHash": 710860076,
                            "iconPath": "",
                            "isActive": true,
                            "visible": false
                        }, {
                            "perkHash": 3703856239,
                            "iconPath": "/common/destiny2_content/icons/92111c4f872db8112e71a1bb4c684609.png",
                            "isActive": true,
                            "visible": true
                        }, {
                            "perkHash": 1776204874,
                            "iconPath": "/common/destiny2_content/icons/0f58c76120e6331c0ee2832c6e8c58fe.png",
                            "isActive": true,
                            "visible": true
                        }]
                    },
                    "45": {
                        "perks": [{
                            "perkHash": 682617678,
                            "iconPath": "/common/destiny2_content/icons/d1ff65162c4a9d54a9612d9874b9fa88.png",
                            "isActive": true,
                            "visible": true
                        }, {
                            "perkHash": 3041644106,
                            "iconPath": "/common/destiny2_content/icons/feb90291222c7ef1fdb0d7730706d36e.png",
                            "isActive": true,
                            "visible": true
                        }, {
                            "perkHash": 4120345915,
                            "iconPath": "/common/destiny2_content/icons/53ead908917c9156457c7c9dd453d649.png",
                            "isActive": true,
                            "visible": true
                        }, {
                            "perkHash": 2252751995,
                            "iconPath": "",
                            "isActive": true,
                            "visible": false
                        }, {
                            "perkHash": 1776204874,
                            "iconPath": "/common/destiny2_content/icons/0f58c76120e6331c0ee2832c6e8c58fe.png",
                            "isActive": true,
                            "visible": true
                        }]
                    },
                    "51": {
                        "perks": [{
                            "perkHash": 279556661,
                            "iconPath": "",
                            "isActive": true,
                            "visible": false
                        }, {
                            "perkHash": 1907936296,
                            "iconPath": "/common/destiny2_content/icons/ad56b0e83d31592d9984cdf2f392452a.png",
                            "isActive": true,
                            "visible": true
                        }, {
                            "perkHash": 1537859493,
                            "iconPath": "/common/destiny2_content/icons/f271b1b0d4ae393cce12eb7c305f8d12.png",
                            "isActive": true,
                            "visible": true
                        }, {
                            "perkHash": 3458972548,
                            "iconPath": "/common/destiny2_content/icons/49df9d90b3f27bd5ec6a9b35f4c10def.png",
                            "isActive": true,
                            "visible": true
                        }, {
                            "perkHash": 2198256770,
                            "iconPath": "/common/destiny2_content/icons/6e67f277fe19b93159c466a41542b7b3.png",
                            "isActive": true,
                            "visible": true
                        }]
                    },
                    "52": {
                        "perks": [{
                            "perkHash": 1717910801,
                            "iconPath": "",
                            "isActive": true,
                            "visible": false
                        }, {
                            "perkHash": 2608136408,
                            "iconPath": "/common/destiny2_content/icons/0ab090e93e19da9e841b0f94c5ab7de6.png",
                            "isActive": true,
                            "visible": true
                        }, {
                            "perkHash": 3527390035,
                            "iconPath": "/common/destiny2_content/icons/d355b1117307c9f187729249361cecc3.png",
                            "isActive": true,
                            "visible": true
                        }, {
                            "perkHash": 1056770387,
                            "iconPath": "",
                            "isActive": true,
                            "visible": false
                        }, {
                            "perkHash": 1314569399,
                            "iconPath": "/common/destiny2_content/icons/b7106e2123d59e57a1547bc006892ebc.png",
                            "isActive": true,
                            "visible": true
                        }, {
                            "perkHash": 1697350647,
                            "iconPath": "/common/destiny2_content/icons/e41eeced6fd09493f6ba87e3cd20112f.png",
                            "isActive": true,
                            "visible": true
                        }]
                    },
                    "56": {
                        "perks": [{
                            "perkHash": 3486450016,
                            "iconPath": "",
                            "isActive": true,
                            "visible": false
                        }, {
                            "perkHash": 3833153424,
                            "iconPath": "/common/destiny2_content/icons/59597c84cf53f7739337a19b80f2d8fe.png",
                            "isActive": true,
                            "visible": true
                        }, {
                            "perkHash": 983157083,
                            "iconPath": "/common/destiny2_content/icons/27372dd0065672d9308804a2a0a442bd.png",
                            "isActive": true,
                            "visible": true
                        }, {
                            "perkHash": 4073730730,
                            "iconPath": "",
                            "isActive": false,
                            "visible": false
                        }, {
                            "perkHash": 3835132082,
                            "iconPath": "/common/destiny2_content/icons/8a42d3e3d7b4c1c38755f5e0ac186f0b.png",
                            "isActive": true,
                            "visible": true
                        }, {
                            "perkHash": 3558172203,
                            "iconPath": "/common/destiny2_content/icons/0dbd2b11fd1343c11b4559c7a72ae8da.png",
                            "isActive": true,
                            "visible": true
                        }]
                    },
                    "116": {
                        "perks": [{
                            "perkHash": 2778772943,
                            "iconPath": "/common/destiny2_content/icons/ad98275db78d2e2dc1090b6fb37f25f9.png",
                            "isActive": true,
                            "visible": true
                        }, {
                            "perkHash": 1345104071,
                            "iconPath": "",
                            "isActive": true,
                            "visible": false
                        }, {
                            "perkHash": 726152835,
                            "iconPath": "/common/destiny2_content/icons/5a0d5a3d14438df3367cd6cafa830dbd.png",
                            "isActive": true,
                            "visible": true
                        }]
                    }
                },
                "privacy": 2
            }
        },
        "currencyLookups": {
            "privacy": 2
        },
        "stringVariables": {
            "privacy": 2
        }
    },
    "ErrorCode": 1,
    "ThrottleSeconds": 0,
    "ErrorStatus": "Success",
    "Message": "Ok",
    "MessageData": {}
}
